click_with_aliasing/__init__.py
click_with_aliasing/argument.py
click_with_aliasing/command.py
click_with_aliasing/group.py
click_with_aliasing/option.py
click_with_aliasing/rule.py
click_with_aliasing-1.2.1.dist-info/licenses/LICENSE
click_with_aliasing-1.2.1.dist-info/METADATA
click_with_aliasing-1.2.1.dist-info/WHEEL
click_with_aliasing-1.2.1.dist-info/top_level.txt
click_with_aliasing-1.2.1.dist-info/RECORD
