Metadata-Version: 2.4
Name: click_with_aliasing
Version: 1.2.1
Summary: A library that allows you to add aliases to your Click group and commands.
Author-email: Marcus Fredriksson <marcus@marcusfredriksson.com>
License: MIT License
Project-URL: Homepage, https://github.com/marcusfrdk/click-with-aliasing
Project-URL: Repository, https://github.com/marcusfrdk/click-with-aliasing
Project-URL: Issues, https://github.com/marcusfrdk/click-with-aliasing/issues
Keywords: click,alias,group,command
Classifier: License :: OSI Approved :: MIT License
Classifier: Programming Language :: Python :: 3
Classifier: Operating System :: OS Independent
Requires-Python: >=3.10
License-File: LICENSE
Requires-Dist: click>=8.1.8
Provides-Extra: build
Requires-Dist: build; extra == "build"
Requires-Dist: twine; extra == "build"
Provides-Extra: dev
Requires-Dist: black>=24.10.0; extra == "dev"
Requires-Dist: pytest>=8.3.4; extra == "dev"
Requires-Dist: isort>=5.13.2; extra == "dev"
Requires-Dist: pylint>=3.3.2; extra == "dev"
Requires-Dist: pre-commit>=4.0.1; extra == "dev"
Requires-Dist: mypy>=1.18.2; extra == "dev"
Dynamic: license-file
